{"assets":{"5EF874FB453906EC059E60CDD33DE05B":{"type":"texture","index":0,"url":{"native":"assets\/3A789CD9-94FA-4EE4-99EF-97D3DA892B31.pdf"},"width":1440,"height":810},"DED684EBAC5033DCD0C434EB5056F616":{"type":"texture","index":1,"url":{"native":"assets\/3A789CD9-94FA-4EE4-99EF-97D3DA892B31.pdf"},"width":1440,"height":810}},"events":[{"effects":[{"beginTime":0,"baseLayer":{"animations":[],"initialState":{"affineTransform":[1,0,0,1,0,0],"masksToBounds":false,"rotation":0,"scale":1,"position":{"pointX":720,"pointY":405},"width":1440,"sublayerTransform":[1,0,0,0,0,1,0,0,0,0,1,0,0,0,0,1],"contentsRect":{"y":0,"x":0,"width":1,"height":1},"opacity":1,"edgeAntialiasingMask":251658240,"height":810,"hidden":false,"anchorPoint":{"pointX":0.5,"pointY":0.5}},"objectID":"0","layers":[{"animations":[],"initialState":{"affineTransform":[1,0,0,1,0,0],"masksToBounds":false,"rotation":0,"scale":1,"position":{"pointX":720,"pointY":405},"width":1440,"sublayerTransform":[1,0,0,0,0,1,0,0,0,0,1,-0.00046677216622367974,0,0,0,1],"contentsRect":{"y":0,"x":0,"width":1,"height":1},"opacity":1,"edgeAntialiasingMask":251658240,"height":810,"hidden":false,"anchorPoint":{"pointX":0.5,"pointY":0.5}},"layers":[{"animations":[],"layers":[],"texturedRectangle":{"isBackgroundTexture":false,"singleTextureOpacity":1,"textureType":0,"textBaseline":0,"textXHeight":0,"isVerticalText":false},"initialState":{"affineTransform":[1,0,0,1,0,0],"masksToBounds":false,"rotation":0,"scale":1,"position":{"pointX":720,"pointY":405},"width":1440,"sublayerTransform":[1,0,0,0,0,1,0,0,0,0,1,0,0,0,0,1],"contentsRect":{"y":0,"x":0,"width":1,"height":1},"opacity":1,"edgeAntialiasingMask":0,"height":810,"hidden":false,"anchorPoint":{"pointX":0.5,"pointY":0.5}},"texture":"DED684EBAC5033DCD0C434EB5056F616"},{"animations":[{"additive":false,"timeOffset":0,"beginTime":0,"from":{"scalar":false},"repeatCount":0,"fillMode":"both","duration":0.001,"autoreverses":false,"property":"hidden","to":{"scalar":true},"removedOnCompletion":false}],"layers":[],"texturedRectangle":{"isBackgroundTexture":false,"singleTextureOpacity":1,"textureType":0,"textBaseline":0,"textXHeight":0,"isVerticalText":false},"initialState":{"affineTransform":[1,0,0,1,0,0],"masksToBounds":false,"rotation":0,"scale":1,"position":{"pointX":720,"pointY":405},"width":1440,"sublayerTransform":[1,0,0,0,0,1,0,0,0,0,1,0,0,0,0,1],"contentsRect":{"y":0,"x":0,"width":1,"height":1},"opacity":1,"edgeAntialiasingMask":0,"height":810,"hidden":false,"anchorPoint":{"pointX":0.5,"pointY":0.5}},"texture":"5EF874FB453906EC059E60CDD33DE05B"}]}]},"effects":[],"duration":0.001,"type":"transition","attributes":{"direction":0},"name":"none","objectID":"0"}],"automaticPlay":false,"hyperlinks":[],"accessibility":[{"text":"￼","targetRectangle":{"y":751.12005579471588,"x":1388.4106656908989,"width":16.796000000000049,"height":18}},{"text":"Global companion mode saw","targetRectangle":{"y":196.34466552734375,"x":68.168121337890625,"width":483.4079999999999,"height":49}},{"text":"11x ","targetRectangle":{"y":248.44856262207031,"x":68.068794250488281,"width":181.82400000000001,"height":131}},{"text":"___.png","targetRectangle":{"y":190.11647033691406,"x":57.963306427001953,"width":651.43646240234375,"height":429.76705932617188}},{"text":"engagement than the “homepage ask a question widget”\\u2028\\u2028\\u2028\\u2028\\u2028\\u2028\\u2028\\u2028\\u2028\\u2028\\u2028\\u2028\\u2028*(Experiment across 2 months, 2M+ user rollout)","targetRectangle":{"y":366.69430541992188,"x":68.068794250488281,"width":439.07999999999998,"height":405}},{"text":"Google Shape;331;p36","targetRectangle":{"y":-2.3747329711914631,"x":-0.12740157544612885,"width":1440.25537109375,"height":388.93750000000017}},{"text":"___.png","targetRectangle":{"y":190.11647033691406,"x":730.60026931762695,"width":651.4364013671875,"height":429.76705932617188}}],"baseLayer":{"animations":[],"initialState":{"affineTransform":[1,0,0,1,0,0],"masksToBounds":false,"rotation":0,"scale":1,"position":{"pointX":720,"pointY":405},"width":1440,"sublayerTransform":[1,0,0,0,0,1,0,0,0,0,1,0,0,0,0,1],"contentsRect":{"y":0,"x":0,"width":1,"height":1},"opacity":1,"edgeAntialiasingMask":251658240,"height":810,"hidden":false,"anchorPoint":{"pointX":0.5,"pointY":0.5}},"objectID":"0","layers":[{"animations":[],"initialState":{"affineTransform":[1,0,0,1,0,0],"masksToBounds":false,"rotation":0,"scale":1,"position":{"pointX":720,"pointY":405},"width":1440,"sublayerTransform":[1,0,0,0,0,1,0,0,0,0,1,-0.00046677216622367974,0,0,0,1],"contentsRect":{"y":0,"x":0,"width":1,"height":1},"opacity":1,"edgeAntialiasingMask":251658240,"height":810,"hidden":false,"anchorPoint":{"pointX":0.5,"pointY":0.5}},"layers":[{"animations":[],"layers":[],"texturedRectangle":{"isBackgroundTexture":false,"singleTextureOpacity":1,"textureType":0,"textBaseline":0,"textXHeight":0,"isVerticalText":false},"initialState":{"affineTransform":[1,0,0,1,0,0],"masksToBounds":false,"rotation":0,"scale":1,"position":{"pointX":720,"pointY":405},"width":1440,"sublayerTransform":[1,0,0,0,0,1,0,0,0,0,1,0,0,0,0,1],"contentsRect":{"y":0,"x":0,"width":1,"height":1},"opacity":1,"edgeAntialiasingMask":0,"height":810,"hidden":false,"anchorPoint":{"pointX":0.5,"pointY":0.5}},"texture":"5EF874FB453906EC059E60CDD33DE05B"}]}]}}]}